dbinterpy/__init__.py
dbinterpy/interface.py
dbinterpy-0.0.2.dist-info/LICENSE
dbinterpy-0.0.2.dist-info/METADATA
dbinterpy-0.0.2.dist-info/WHEEL
dbinterpy-0.0.2.dist-info/top_level.txt
dbinterpy-0.0.2.dist-info/RECORD
